termicod/__init__.py
termicod-1.0.0.dist-info/LICENSE.txt
termicod-1.0.0.dist-info/METADATA
termicod-1.0.0.dist-info/WHEEL
termicod-1.0.0.dist-info/top_level.txt
termicod-1.0.0.dist-info/RECORD
