Metadata-Version: 2.1
Name: termicod
Version: 1.0.0
Summary: Renders Progress Bars & Coloured Text In The Terminal!! 
Author: Pigeon Nation
License: MIT
Classifier: Programming Language :: Python :: 3
Classifier: License :: OSI Approved :: MIT License
Classifier: Operating System :: OS Independent
Classifier: Topic :: Other/Nonlisted Topic
License-File: LICENSE.txt
